majordomo_llm/__init__.py
majordomo_llm/base.py
majordomo_llm/cascade.py
majordomo_llm/exceptions.py
majordomo_llm/factory.py
majordomo_llm/llm_config.yaml
majordomo_llm/py.typed
majordomo_llm/logging/__init__.py
majordomo_llm/logging/interfaces.py
majordomo_llm/logging/models.py
majordomo_llm/logging/schema.sql
majordomo_llm/logging/wrapper.py
majordomo_llm/logging/adapters/__init__.py
majordomo_llm/logging/adapters/file.py
majordomo_llm/logging/adapters/mysql.py
majordomo_llm/logging/adapters/postgres.py
majordomo_llm/logging/adapters/s3.py
majordomo_llm/logging/adapters/sqlite.py
majordomo_llm/providers/__init__.py
majordomo_llm/providers/anthropic.py
majordomo_llm/providers/cohere.py
majordomo_llm/providers/deepseek.py
majordomo_llm/providers/gemini.py
majordomo_llm/providers/openai.py
majordomo_llm-0.1.6.dist-info/METADATA
majordomo_llm-0.1.6.dist-info/WHEEL
majordomo_llm-0.1.6.dist-info/licenses/LICENSE
majordomo_llm-0.1.6.dist-info/RECORD
