Metadata-Version: 2.4
Name: majordomo-llm
Version: 0.1.6
Summary: Unified Python interface for multiple LLM providers with cost tracking
Project-URL: Homepage, https://github.com/superset-studio/majordomo-llm
Project-URL: Documentation, https://github.com/superset-studio/majordomo-llm#readme
Project-URL: Repository, https://github.com/superset-studio/majordomo-llm
Project-URL: Issues, https://github.com/superset-studio/majordomo-llm/issues
Project-URL: Changelog, https://github.com/superset-studio/majordomo-llm/blob/main/CHANGELOG.md
Author-email: Vivek Vaidya <vivek@superset.com>
License: MIT
License-File: LICENSE
Keywords: ai,anthropic,async,claude,cohere,gemini,gpt,llm,machine-learning,openai
Classifier: Development Status :: 4 - Beta
Classifier: Framework :: AsyncIO
Classifier: Intended Audience :: Developers
Classifier: License :: OSI Approved :: MIT License
Classifier: Operating System :: OS Independent
Classifier: Programming Language :: Python :: 3
Classifier: Programming Language :: Python :: 3.12
Classifier: Programming Language :: Python :: 3.13
Classifier: Topic :: Scientific/Engineering :: Artificial Intelligence
Classifier: Typing :: Typed
Requires-Python: >=3.12
Requires-Dist: anthropic>=0.76.0
Requires-Dist: cohere>=5.1.8
Requires-Dist: google-genai>=1.60.0
Requires-Dist: openai>=2.15.0
Requires-Dist: pre-commit>=4.5.1
Requires-Dist: pydantic>=2.12.5
Requires-Dist: pyyaml>=6.0
Requires-Dist: tenacity>=9.1.2
Provides-Extra: dev
Requires-Dist: aioboto3>=13.0.0; extra == 'dev'
Requires-Dist: aiofiles>=24.0.0; extra == 'dev'
Requires-Dist: aiomysql>=0.2.0; extra == 'dev'
Requires-Dist: aiosqlite>=0.20.0; extra == 'dev'
Requires-Dist: asyncpg>=0.29.0; extra == 'dev'
Requires-Dist: mypy>=1.14.0; extra == 'dev'
Requires-Dist: pytest-asyncio>=0.24.0; extra == 'dev'
Requires-Dist: pytest-cov>=6.0.0; extra == 'dev'
Requires-Dist: pytest>=8.0.0; extra == 'dev'
Requires-Dist: python-dotenv>=1.0.0; extra == 'dev'
Requires-Dist: ruff>=0.9.0; extra == 'dev'
Provides-Extra: logging
Requires-Dist: aioboto3>=13.0.0; extra == 'logging'
Requires-Dist: aiofiles>=24.0.0; extra == 'logging'
Requires-Dist: aiomysql>=0.2.0; extra == 'logging'
Requires-Dist: aiosqlite>=0.20.0; extra == 'logging'
Requires-Dist: asyncpg>=0.29.0; extra == 'logging'
